tests/__init__.py
tests/test_generator.py
tests/test_generator_methods.py
tests/test_generatorsupport.py
tests/test_localizer.py
tksugar/__init__.py
tksugar/eventreciever.py
tksugar/generator.py
tksugar/localizer.py
tksugar/tkmanager.py
tksugar/widgets/__init__.py
tksugar/widgets/generatorsupport.py
tksugar/widgets/menu.py
tksugar/widgets/notebook.py
tksugar-0.1.3.dist-info/LICENSE
tksugar-0.1.3.dist-info/METADATA
tksugar-0.1.3.dist-info/WHEEL
tksugar-0.1.3.dist-info/top_level.txt
tksugar-0.1.3.dist-info/RECORD
