Metadata-Version: 2.1
Name: tksugar
Version: 0.1.3
Summary: A module that generates a structured Tk window frame from a text file.
Home-page: https://github.com/TakamiChie/TkSugar
Author: TakamiChie
Author-email: chie@onpu-tamago.net
License: MIT
Platform: UNKNOWN
Classifier: Programming Language :: Python :: 3.7
Classifier: Programming Language :: Python :: 3.8
Classifier: Programming Language :: Python :: 3.9
Requires-Dist: pyyaml
Requires-Dist: pyyaml-include
